soft_delete/__init__.py
soft_delete/delete_history.py
soft_delete/models.py
karthiksp_softdelete-0.0.1.dist-info/LICENSE
karthiksp_softdelete-0.0.1.dist-info/METADATA
karthiksp_softdelete-0.0.1.dist-info/WHEEL
karthiksp_softdelete-0.0.1.dist-info/top_level.txt
karthiksp_softdelete-0.0.1.dist-info/RECORD
